MANIFEST.in
README.md
setup.cfg
setup.py
golden_borders/__init__.py
golden_borders.egg-info/PKG-INFO
golden_borders.egg-info/SOURCES.txt
golden_borders.egg-info/dependency_links.txt
golden_borders.egg-info/entry_points.txt
golden_borders.egg-info/requires.txt
golden_borders.egg-info/top_level.txt
golden_borders.egg-info/zip-safe