Metadata-Version: 2.1
Name: golden-borders
Version: 1.2.0
Summary: Optically center the window of a print by computing the mat/print sizes.
Home-page: https://github.com/semond/golden-borders
Author: Serge Émond
Author-email: serge@sergeemond.com
License: UNKNOWN
Platform: UNKNOWN
Classifier: Development Status :: 5 - Production/Stable
Classifier: Environment :: Console
Classifier: License :: OSI Approved :: BSD License
Classifier: Topic :: Utilities
Requires-Python: >=3.3
Provides-Extra: dev
